omibio/__init__.py
omibio/analysis/__init__.py
omibio/analysis/consensus.py
omibio/analysis/find_motif.py
omibio/analysis/find_orfs.py
omibio/analysis/gc_content.py
omibio/analysis/kmer.py
omibio/analysis/palindrome.py
omibio/analysis/protein_mass.py
omibio/analysis/sliding_gc.py
omibio/bio/__init__.py
omibio/bio/analysis_result.py
omibio/bio/interval_result.py
omibio/bio/kmer_result.py
omibio/bio/seq_collections.py
omibio/bio/seq_entry.py
omibio/bio/seq_interval.py
omibio/cli/__init__.py
omibio/cli/random_fasta_cli.py
omibio/cli/fasta_cli/__init__.py
omibio/cli/fasta_cli/fasta_clean.py
omibio/cli/fasta_cli/fasta_info.py
omibio/cli/fasta_cli/fasta_shuffle.py
omibio/cli/fasta_cli/fasta_view.py
omibio/cli/fastq_cli/__init__.py
omibio/cli/fastq_cli/fastq_info.py
omibio/cli/fastq_cli/fastq_to_fasta.py
omibio/cli/fastq_cli/fastq_view.py
omibio/cli/gc_cli/__init__.py
omibio/cli/gc_cli/gc_compute.py
omibio/cli/gc_cli/gc_sliding_window.py
omibio/cli/kmer_cli/__init__.py
omibio/cli/kmer_cli/kmer_count.py
omibio/cli/kmer_cli/kmer_total.py
omibio/cli/orf_cli/__init__.py
omibio/cli/orf_cli/orf_find.py
omibio/cli/plot_cli/__init__.py
omibio/cli/plot_cli/plot_kmer_cli.py
omibio/cli/plot_cli/plot_window_gc_cli.py
omibio/io/__init__.py
omibio/io/read_fasta.py
omibio/io/read_fastq.py
omibio/io/write_fasta.py
omibio/io/write_fastq.py
omibio/sequence/__init__.py
omibio/sequence/polypeptide.py
omibio/sequence/sequence.py
omibio/sequence/seq_utils/__init__.py
omibio/sequence/seq_utils/clean.py
omibio/sequence/seq_utils/complement.py
omibio/sequence/seq_utils/random_seq.py
omibio/sequence/seq_utils/shuffle_seq.py
omibio/sequence/seq_utils/transcribe.py
omibio/sequence/seq_utils/translate.py
omibio/utils/__init__.py
omibio/utils/truncate_repr.py
omibio/viz/__init__.py
omibio/viz/plot_kmer_heatmap.py
omibio/viz/plot_motifs.py
omibio/viz/plot_orfs.py
omibio/viz/plot_sliding_gc.py
omibio-0.1.4.post3.dist-info/licenses/LICENSE
omibio-0.1.4.post3.dist-info/METADATA
omibio-0.1.4.post3.dist-info/WHEEL
omibio-0.1.4.post3.dist-info/entry_points.txt
omibio-0.1.4.post3.dist-info/top_level.txt
omibio-0.1.4.post3.dist-info/RECORD
