Metadata-Version: 2.4
Name: omibio
Version: 0.1.4.post3
Summary: A lightweight and easy-to-use Python bioinformatics toolkit.
Author: OceanMist
License-Expression: MIT
Keywords: bioinformatics,omics,sequence-analysis,computational-biology
Classifier: Development Status :: 3 - Alpha
Classifier: Intended Audience :: Science/Research
Classifier: Programming Language :: Python :: 3
Classifier: Programming Language :: Python :: 3.11
Classifier: Programming Language :: Python :: 3.12
Classifier: Programming Language :: Python :: 3.13
Classifier: Topic :: Scientific/Engineering :: Bio-Informatics
Requires-Python: >=3.11
License-File: LICENSE
Requires-Dist: click
Requires-Dist: numpy
Requires-Dist: pandas
Requires-Dist: matplotlib
Requires-Dist: seaborn
Provides-Extra: dev
Requires-Dist: pytest>=7; extra == "dev"
Requires-Dist: pytest-cov; extra == "dev"
Requires-Dist: black>=23; extra == "dev"
Requires-Dist: isort; extra == "dev"
Requires-Dist: mypy>=1; extra == "dev"
Requires-Dist: ruff; extra == "dev"
Provides-Extra: all
Requires-Dist: omibio[dev]; extra == "all"
Dynamic: license-file
